{
  "fields": [
    {
      "aggregatable": true,
      "custom": false,
      "defaultValue": null,
      "extraTypeInfo": null,
      "filterable": true,
      "groupable": true,
      "inlineHelpText": null,
      "label": "Custom Link ID",
      "name": "Id",
      "nillable": false,
      "picklistValues": [],
      "referenceTo": [],
      "relationshipName": null,
      "sortable": true,
      "type": "id"
    },
    {
      "aggregatable": true,
      "custom": false,
      "defaultValue": null,
      "extraTypeInfo": null,
      "filterable": true,
      "groupable": true,
      "inlineHelpText": null,
      "label": "Page or sObject Type Name",
      "name": "PageOrSobjectType",
      "nillable": false,
      "picklistValues": [
        {
          "active": true,
          "defaultValue": false,
          "label": null,
          "validFor": null,
          "value": "Account"
        },
        {
          "active": true,
          "defaultValue": false,
          "label": null,
          "validFor": null,
          "value": "AccountBrand"
        },
        {
          "active": true,
          "defaultValue": false,
          "label": null,
          "validFor": null,
          "value": "AccountContactRelation"
        },
        {
          "active": true,
          "defaultValue": false,
          "label": null,
          "validFor": null,
          "value": "AccountTeamMember"
        },
        {
          "active": true,
          "defaultValue": false,
          "label": null,
          "validFor": null,
          "value": "Activity"
        },
        {
          "active": true,
          "defaultValue": false,
          "label": null,
          "validFor": null,
          "value": "agf__ADM_Acceptance_Criterion__c"
        },
        {
          "active": true,
          "defaultValue": false,
          "label": null,
          "validFor": null,
          "value": "agf__ADM_Additional_Field__c"
        },
        {
          "active": true,
          "defaultValue": false,
          "label": null,
          "validFor": null,
          "value": "agf__ADM_Application__c"
        },
        {
          "active": true,
          "defaultValue": false,
          "label": null,
          "validFor": null,
          "value": "agf__ADM_Application_Approver__c"
        },
        {
          "active": true,
          "defaultValue": false,
          "label": null,
          "validFor": null,
          "value": "agf__ADM_Assignment_Rule__c"
        },
        {
          "active": true,
          "defaultValue": false,
          "label": null,
          "validFor": null,
          "value": "agf__ADM_Bookmark__c"
        },
        {
          "active": true,
          "defaultValue": false,
          "label": null,
          "validFor": null,
          "value": "agf__ADM_Build__c"
        },
        {
          "active": true,
          "defaultValue": false,
          "label": null,
          "validFor": null,
          "value": "agf__ADM_Burndown_Item__c"
        },
        {
          "active": true,
          "defaultValue": false,
          "label": null,
          "validFor": null,
          "value": "agf__ADM_Cache_Metadata__mdt"
        },
        {
          "active": true,
          "defaultValue": false,
          "label": null,
          "validFor": null,
          "value": "agf__ADM_Case__c"
        },
        {
          "active": true,
          "defaultValue": false,
          "label": null,
          "validFor": null,
          "value": "agf__ADM_Certification__c"
        },
        {
          "active": true,
          "defaultValue": false,
          "label": null,
          "validFor": null,
          "value": "agf__ADM_Change_List__c"
        },
        {
          "active": true,
          "defaultValue": false,
          "label": null,
          "validFor": null,
          "value": "agf__ADM_Cloud__c"
        },
        {
          "active": true,
          "defaultValue": false,
          "label": null,
          "validFor": null,
          "value": "agf__ADM_Color__c"
        },
        {
          "active": true,
          "defaultValue": false,
          "label": null,
          "validFor": null,
          "value": "agf__ADM_Column__c"
        },
        {
          "active": true,
          "defaultValue": false,
          "label": null,
          "validFor": null,
          "value": "agf__ADM_Column_History__c"
        },
        {
          "active": true,
          "defaultValue": false,
          "label": null,
          "validFor": null,
          "value": "agf__ADM_Column_Status_Assignment__c"
        },
        {
          "active": true,
          "defaultValue": false,
          "label": null,
          "validFor": null,
          "value": "agf__ADM_Comment__c"
        },
        {
          "active": true,
          "defaultValue": false,
          "label": null,
          "validFor": null,
          "value": "agf__ADM_Copy_Log__c"
        },
        {
          "active": true,
          "defaultValue": false,
          "label": null,
          "validFor": null,
          "value": "agf__ADM_Coverage__c"
        },
        {
          "active": true,
          "defaultValue": false,
          "label": null,
          "validFor": null,
          "value": "agf__ADM_Deleted_Task__c"
        },
        {
          "active": true,
          "defaultValue": false,
          "label": null,
          "validFor": null,
          "value": "agf__ADM_Epic__c"
        },
        {
          "active": true,
          "defaultValue": false,
          "label": null,
          "validFor": null,
          "value": "agf__ADM_Epic_Burndown_Item__c"
        },
        {
          "active": true,
          "defaultValue": false,
          "label": null,
          "validFor": null,
          "value": "agf__ADM_Feature_Freeze_Exception_Request__c"
        },
        {
          "active": true,
          "defaultValue": false,
          "label": null,
          "validFor": null,
          "value": "agf__ADM_Feature_Freeze_Status__c"
        },
        {
          "active": true,
          "defaultValue": false,
          "label": null,
          "validFor": null,
          "value": "agf__ADM_Frequency__c"
        },
        {
          "active": true,
          "defaultValue": false,
          "label": null,
          "validFor": null,
          "value": "agf__ADM_Goal__c"
        },
        {
          "active": true,
          "defaultValue": false,
          "label": null,
          "validFor": null,
          "value": "agf__ADM_GUS_Exception__c"
        },
        {
          "active": true,
          "defaultValue": false,
          "label": null,
          "validFor": null,
          "value": "agf__ADM_Impact__c"
        },
        {
          "active": true,
          "defaultValue": false,
          "label": null,
          "validFor": null,
          "value": "agf__ADM_Impact_Type__c"
        },
        {
          "active": true,
          "defaultValue": false,
          "label": null,
          "validFor": null,
          "value": "agf__ADM_Investigation_Exception__c"
        },
        {
          "active": true,
          "defaultValue": false,
          "label": null,
          "validFor": null,
          "value": "agf__ADM_Key_Value_Properties__c"
        },
        {
          "active": true,
          "defaultValue": false,
          "label": null,
          "validFor": null,
          "value": "agf__ADM_Parent_Cloud__c"
        },
        {
          "active": true,
          "defaultValue": false,
          "label": null,
          "validFor": null,
          "value": "agf__ADM_Parent_Work__c"
        },
        {
          "active": true,
          "defaultValue": false,
          "label": null,
          "validFor": null,
          "value": "agf__ADM_Perforce_Connector__c"
        },
        {
          "active": true,
          "defaultValue": false,
          "label": null,
          "validFor": null,
          "value": "agf__ADM_Priority__c"
        },
        {
          "active": true,
          "defaultValue": false,
          "label": null,
          "validFor": null,
          "value": "agf__ADM_Priority_Mapping__c"
        },
        {
          "active": true,
          "defaultValue": false,
          "label": null,
          "validFor": null,
          "value": "agf__ADM_Priority_Override__c"
        },
        {
          "active": true,
          "defaultValue": false,
          "label": null,
          "validFor": null,
          "value": "agf__ADM_Product_Tag__c"
        },
        {
          "active": true,
          "defaultValue": false,
          "label": null,
          "validFor": null,
          "value": "agf__ADM_Product_Tag_Work_Metadata__c"
        },
        {
          "active": true,
          "defaultValue": false,
          "label": null,
          "validFor": null,
          "value": "agf__ADM_Release__c"
        },
        {
          "active": true,
          "defaultValue": false,
          "label": null,
          "validFor": null,
          "value": "agf__ADM_Release_Burndown_Item__c"
        },
        {
          "active": true,
          "defaultValue": false,
          "label": null,
          "validFor": null,
          "value": "agf__ADM_Release_Event__c"
        },
        {
          "active": true,
          "defaultValue": false,
          "label": null,
          "validFor": null,
          "value": "agf__ADM_Release_Event_Template__c"
        },
        {
          "active": true,
          "defaultValue": false,
          "label": null,
          "validFor": null,
          "value": "agf__ADM_Release_Freeze_Status__c"
        },
        {
          "active": true,
          "defaultValue": false,
          "label": null,
          "validFor": null,
          "value": "agf__ADM_Release_Signoff__c"
        },
        {
          "active": true,
          "defaultValue": false,
          "label": null,
          "validFor": null,
          "value": "agf__ADM_Release_Stamp_Batch_ID__c"
        },
        {
          "active": true,
          "defaultValue": false,
          "label": null,
          "validFor": null,
          "value": "agf__ADM_Release_Stamp_Cache__c"
        },
        {
          "active": true,
          "defaultValue": false,
          "label": null,
          "validFor": null,
          "value": "agf__ADM_Released_In__c"
        },
        {
          "active": true,
          "defaultValue": false,
          "label": null,
          "validFor": null,
          "value": "agf__ADM_Scrum_Team__c"
        },
        {
          "active": true,
          "defaultValue": false,
          "label": null,
          "validFor": null,
          "value": "agf__ADM_Scrum_Team_Cache__c"
        },
        {
          "active": true,
          "defaultValue": false,
          "label": null,
          "validFor": null,
          "value": "agf__ADM_Scrum_Team_Member__c"
        },
        {
          "active": true,
          "defaultValue": false,
          "label": null,
          "validFor": null,
          "value": "agf__ADM_Security_Questionaire__c"
        },
        {
          "active": true,
          "defaultValue": false,
          "label": null,
          "validFor": null,
          "value": "agf__ADM_Severity__c"
        },
        {
          "active": true,
          "defaultValue": false,
          "label": null,
          "validFor": null,
          "value": "agf__ADM_Severity_Type__c"
        },
        {
          "active": true,
          "defaultValue": false,
          "label": null,
          "validFor": null,
          "value": "agf__ADM_Solution_Overview__c"
        },
        {
          "active": true,
          "defaultValue": false,
          "label": null,
          "validFor": null,
          "value": "agf__ADM_Sprint__c"
        },
        {
          "active": true,
          "defaultValue": false,
          "label": null,
          "validFor": null,
          "value": "agf__ADM_Status_History__c"
        },
        {
          "active": true,
          "defaultValue": false,
          "label": null,
          "validFor": null,
          "value": "agf__ADM_Tag_Assignment__c"
        },
        {
          "active": true,
          "defaultValue": false,
          "label": null,
          "validFor": null,
          "value": "agf__ADM_Task__c"
        },
        {
          "active": true,
          "defaultValue": false,
          "label": null,
          "validFor": null,
          "value": "agf__ADM_Team_Dependency__c"
        },
        {
          "active": true,
          "defaultValue": false,
          "label": null,
          "validFor": null,
          "value": "agf__ADM_Team_Name_History__c"
        },
        {
          "active": true,
          "defaultValue": false,
          "label": null,
          "validFor": null,
          "value": "agf__ADM_Team_Release__c"
        },
        {
          "active": true,
          "defaultValue": false,
          "label": null,
          "validFor": null,
          "value": "agf__ADM_Theme__c"
        },
        {
          "active": true,
          "defaultValue": false,
          "label": null,
          "validFor": null,
          "value": "agf__ADM_Theme_Assignment__c"
        },
        {
          "active": true,
          "defaultValue": false,
          "label": null,
          "validFor": null,
          "value": "agf__ADM_Third_Party_Software__c"
        },
        {
          "active": true,
          "defaultValue": false,
          "label": null,
          "validFor": null,
          "value": "agf__ADM_Time_Off_Log__c"
        },
        {
          "active": true,
          "defaultValue": false,
          "label": null,
          "validFor": null,
          "value": "agf__ADM_Type__c"
        },
        {
          "active": true,
          "defaultValue": false,
          "label": null,
          "validFor": null,
          "value": "agf__ADM_User_Business_Hours__c"
        },
        {
          "active": true,
          "defaultValue": false,
          "label": null,
          "validFor": null,
          "value": "agf__ADM_User_Product_Tag__c"
        },
        {
          "active": true,
          "defaultValue": false,
          "label": null,
          "validFor": null,
          "value": "agf__ADM_Valid_GUS_Value__c"
        },
        {
          "active": true,
          "defaultValue": false,
          "label": null,
          "validFor": null,
          "value": "agf__ADM_Work__c"
        },
        {
          "active": true,
          "defaultValue": false,
          "label": null,
          "validFor": null,
          "value": "agf__ADM_Work_Cache__c"
        },
        {
          "active": true,
          "defaultValue": false,
          "label": null,
          "validFor": null,
          "value": "agf__ADM_Work_Commitment__c"
        },
        {
          "active": true,
          "defaultValue": false,
          "label": null,
          "validFor": null,
          "value": "agf__ADM_Work_History__c"
        },
        {
          "active": true,
          "defaultValue": false,
          "label": null,
          "validFor": null,
          "value": "agf__ADM_Work_SLA_Response_Time__mdt"
        },
        {
          "active": true,
          "defaultValue": false,
          "label": null,
          "validFor": null,
          "value": "agf__ADM_Work_Status__c"
        },
        {
          "active": true,
          "defaultValue": false,
          "label": null,
          "validFor": null,
          "value": "agf__ADM_Work_Subscriber__c"
        },
        {
          "active": true,
          "defaultValue": false,
          "label": null,
          "validFor": null,
          "value": "agf__ADM_WorkFieldsForRecordType__mdt"
        },
        {
          "active": true,
          "defaultValue": false,
          "label": null,
          "validFor": null,
          "value": "agf__Environments_Order__c"
        },
        {
          "active": true,
          "defaultValue": false,
          "label": null,
          "validFor": null,
          "value": "agf__eRelease_Request__c"
        },
        {
          "active": true,
          "defaultValue": false,
          "label": null,
          "validFor": null,
          "value": "agf__Headcount__c"
        },
        {
          "active": true,
          "defaultValue": false,
          "label": null,
          "validFor": null,
          "value": "agf__Locking_Record__c"
        },
        {
          "active": true,
          "defaultValue": false,
          "label": null,
          "validFor": null,
          "value": "agf__OMOpportunity__c"
        },
        {
          "active": true,
          "defaultValue": false,
          "label": null,
          "validFor": null,
          "value": "agf__PPM_Portfolio__c"
        },
        {
          "active": true,
          "defaultValue": false,
          "label": null,
          "validFor": null,
          "value": "agf__PPM_Program__c"
        },
        {
          "active": true,
          "defaultValue": false,
          "label": null,
          "validFor": null,
          "value": "agf__PPM_Project__c"
        },
        {
          "active": true,
          "defaultValue": false,
          "label": null,
          "validFor": null,
          "value": "agf__PPM_Project_Accomplishment__c"
        },
        {
          "active": true,
          "defaultValue": false,
          "label": null,
          "validFor": null,
          "value": "agf__QA_Answer__c"
        },
        {
          "active": true,
          "defaultValue": false,
          "label": null,
          "validFor": null,
          "value": "agf__QA_Comment__c"
        },
        {
          "active": true,
          "defaultValue": false,
          "label": null,
          "validFor": null,
          "value": "agf__QA_Default_Test_Case__c"
        },
        {
          "active": true,
          "defaultValue": false,
          "label": null,
          "validFor": null,
          "value": "agf__QA_ExecutionBug__c"
        },
        {
          "active": true,
          "defaultValue": false,
          "label": null,
          "validFor": null,
          "value": "agf__QA_FTest__c"
        },
        {
          "active": true,
          "defaultValue": false,
          "label": null,
          "validFor": null,
          "value": "agf__QA_Hierarchy__c"
        },
        {
          "active": true,
          "defaultValue": false,
          "label": null,
          "validFor": null,
          "value": "agf__QA_Question__c"
        },
        {
          "active": true,
          "defaultValue": false,
          "label": null,
          "validFor": null,
          "value": "agf__QA_Test_Case__c"
        },
        {
          "active": true,
          "defaultValue": false,
          "label": null,
          "validFor": null,
          "value": "agf__QA_Test_Execution__c"
        },
        {
          "active": true,
          "defaultValue": false,
          "label": null,
          "validFor": null,
          "value": "agf__QA_Test_Plan__c"
        },
        {
          "active": true,
          "defaultValue": false,
          "label": null,
          "validFor": null,
          "value": "agf__RCA__c"
        },
        {
          "active": true,
          "defaultValue": false,
          "label": null,
          "validFor": null,
          "value": "agf__Release_Signoff_Infrastructure__c"
        },
        {
          "active": true,
          "defaultValue": false,
          "label": null,
          "validFor": null,
          "value": "agf__Retrospective__c"
        },
        {
          "active": true,
          "defaultValue": false,
          "label": null,
          "validFor": null,
          "value": "agf__SLA_Violation__c"
        },
        {
          "active": true,
          "defaultValue": false,
          "label": null,
          "validFor": null,
          "value": "agf__WorkData__c"
        },
        {
          "active": true,
          "defaultValue": false,
          "label": null,
          "validFor": null,
          "value": "Alphabetical_list_of_products__x"
        },
        {
          "active": true,
          "defaultValue": false,
          "label": null,
          "validFor": null,
          "value": "ApiAnomalyEventStore"
        },
        {
          "active": true,
          "defaultValue": false,
          "label": null,
          "validFor": null,
          "value": "Asset"
        },
        {
          "active": true,
          "defaultValue": false,
          "label": null,
          "validFor": null,
          "value": "AssetRelationship"
        },
        {
          "active": true,
          "defaultValue": false,
          "label": null,
          "validFor": null,
          "value": "AuthorizationForm"
        },
        {
          "active": true,
          "defaultValue": false,
          "label": null,
          "validFor": null,
          "value": "AuthorizationFormConsent"
        },
        {
          "active": true,
          "defaultValue": false,
          "label": null,
          "validFor": null,
          "value": "AuthorizationFormDataUse"
        },
        {
          "active": true,
          "defaultValue": false,
          "label": null,
          "validFor": null,
          "value": "AuthorizationFormText"
        },
        {
          "active": true,
          "defaultValue": false,
          "label": null,
          "validFor": null,
          "value": "BusinessBrand"
        },
        {
          "active": true,
          "defaultValue": false,
          "label": null,
          "validFor": null,
          "value": "Campaign"
        },
        {
          "active": true,
          "defaultValue": false,
          "label": null,
          "validFor": null,
          "value": "CampaignMember"
        },
        {
          "active": true,
          "defaultValue": false,
          "label": null,
          "validFor": null,
          "value": "Case"
        },
        {
          "active": true,
          "defaultValue": false,
          "label": null,
          "validFor": null,
          "value": "Categories__x"
        },
        {
          "active": true,
          "defaultValue": false,
          "label": null,
          "validFor": null,
          "value": "Category_Sales_for_1997__x"
        },
        {
          "active": true,
          "defaultValue": false,
          "label": null,
          "validFor": null,
          "value": "Certification__c"
        },
        {
          "active": true,
          "defaultValue": false,
          "label": null,
          "validFor": null,
          "value": "ChannelProgram"
        },
        {
          "active": true,
          "defaultValue": false,
          "label": null,
          "validFor": null,
          "value": "ChannelProgramLevel"
        },
        {
          "active": true,
          "defaultValue": false,
          "label": null,
          "validFor": null,
          "value": "ChannelProgramMember"
        },
        {
          "active": true,
          "defaultValue": false,
          "label": null,
          "validFor": null,
          "value": "CommSubscription"
        },
        {
          "active": true,
          "defaultValue": false,
          "label": null,
          "validFor": null,
          "value": "CommSubscriptionChannelType"
        },
        {
          "active": true,
          "defaultValue": false,
          "label": null,
          "validFor": null,
          "value": "Competency__c"
        },
        {
          "active": true,
          "defaultValue": false,
          "label": null,
          "validFor": null,
          "value": "ConsumptionRate"
        },
        {
          "active": true,
          "defaultValue": false,
          "label": null,
          "validFor": null,
          "value": "ConsumptionSchedule"
        },
        {
          "active": true,
          "defaultValue": false,
          "label": null,
          "validFor": null,
          "value": "Contact"
        },
        {
          "active": true,
          "defaultValue": false,
          "label": null,
          "validFor": null,
          "value": "ContactPointTypeConsent"
        },
        {
          "active": true,
          "defaultValue": false,
          "label": null,
          "validFor": null,
          "value": "ContactRequest"
        },
        {
          "active": true,
          "defaultValue": false,
          "label": null,
          "validFor": null,
          "value": "ContentVersion"
        },
        {
          "active": true,
          "defaultValue": false,
          "label": null,
          "validFor": null,
          "value": "Contract"
        },
        {
          "active": true,
          "defaultValue": false,
          "label": null,
          "validFor": null,
          "value": "CredentialStuffingEventStore"
        },
        {
          "active": true,
          "defaultValue": false,
          "label": null,
          "validFor": null,
          "value": "Current_Product_Lists__x"
        },
        {
          "active": true,
          "defaultValue": false,
          "label": null,
          "validFor": null,
          "value": "Customer"
        },
        {
          "active": true,
          "defaultValue": false,
          "label": null,
          "validFor": null,
          "value": "Customer_and_Suppliers_by_Cities__x"
        },
        {
          "active": true,
          "defaultValue": false,
          "label": null,
          "validFor": null,
          "value": "CustomerDemographics__x"
        },
        {
          "active": true,
          "defaultValue": false,
          "label": null,
          "validFor": null,
          "value": "Customers__x"
        },
        {
          "active": true,
          "defaultValue": false,
          "label": null,
          "validFor": null,
          "value": "CustomPageItem"
        },
        {
          "active": true,
          "defaultValue": false,
          "label": null,
          "validFor": null,
          "value": "DandBCompany"
        },
        {
          "active": true,
          "defaultValue": false,
          "label": null,
          "validFor": null,
          "value": "DashboardComponent"
        },
        {
          "active": true,
          "defaultValue": false,
          "label": null,
          "validFor": null,
          "value": "DataUseLegalBasis"
        },
        {
          "active": true,
          "defaultValue": false,
          "label": null,
          "validFor": null,
          "value": "DataUsePurpose"
        },
        {
          "active": true,
          "defaultValue": false,
          "label": null,
          "validFor": null,
          "value": "DelegatedAccount"
        },
        {
          "active": true,
          "defaultValue": false,
          "label": null,
          "validFor": null,
          "value": "DuplicateRecordItem"
        },
        {
          "active": true,
          "defaultValue": false,
          "label": null,
          "validFor": null,
          "value": "DuplicateRecordSet"
        },
        {
          "active": true,
          "defaultValue": false,
          "label": null,
          "validFor": null,
          "value": "Education__c"
        },
        {
          "active": true,
          "defaultValue": false,
          "label": null,
          "validFor": null,
          "value": "EmailMessage"
        },
        {
          "active": true,
          "defaultValue": false,
          "label": null,
          "validFor": null,
          "value": "Employees__x"
        },
        {
          "active": true,
          "defaultValue": false,
          "label": null,
          "validFor": null,
          "value": "EngagementChannelType"
        },
        {
          "active": true,
          "defaultValue": false,
          "label": null,
          "validFor": null,
          "value": "Event"
        },
        {
          "active": true,
          "defaultValue": false,
          "label": null,
          "validFor": null,
          "value": "Goal"
        },
        {
          "active": true,
          "defaultValue": false,
          "label": null,
          "validFor": null,
          "value": "GoalLink"
        },
        {
          "active": true,
          "defaultValue": false,
          "label": null,
          "validFor": null,
          "value": "Idea"
        },
        {
          "active": true,
          "defaultValue": false,
          "label": null,
          "validFor": null,
          "value": "Image"
        },
        {
          "active": true,
          "defaultValue": false,
          "label": null,
          "validFor": null,
          "value": "Individual"
        },
        {
          "active": true,
          "defaultValue": false,
          "label": null,
          "validFor": null,
          "value": "Invoices__x"
        },
        {
          "active": true,
          "defaultValue": false,
          "label": null,
          "validFor": null,
          "value": "Key_Expertise__c"
        },
        {
          "active": true,
          "defaultValue": false,
          "label": null,
          "validFor": null,
          "value": "Knowledge__kav"
        },
        {
          "active": true,
          "defaultValue": false,
          "label": null,
          "validFor": null,
          "value": "Lead"
        },
        {
          "active": true,
          "defaultValue": false,
          "label": null,
          "validFor": null,
          "value": "LinkedArticle"
        },
        {
          "active": true,
          "defaultValue": false,
          "label": null,
          "validFor": null,
          "value": "Macro"
        },
        {
          "active": true,
          "defaultValue": false,
          "label": null,
          "validFor": null,
          "value": "Message__c"
        },
        {
          "active": true,
          "defaultValue": false,
          "label": null,
          "validFor": null,
          "value": "Metric"
        },
        {
          "active": true,
          "defaultValue": false,
          "label": null,
          "validFor": null,
          "value": "Opportunity"
        },
        {
          "active": true,
          "defaultValue": false,
          "label": null,
          "validFor": null,
          "value": "OpportunityContactRole"
        },
        {
          "active": true,
          "defaultValue": false,
          "label": null,
          "validFor": null,
          "value": "OpportunityLineItem"
        },
        {
          "active": true,
          "defaultValue": false,
          "label": null,
          "validFor": null,
          "value": "Order"
        },
        {
          "active": true,
          "defaultValue": false,
          "label": null,
          "validFor": null,
          "value": "Order_Details__x"
        },
        {
          "active": true,
          "defaultValue": false,
          "label": null,
          "validFor": null,
          "value": "Order_Details_Extendeds__x"
        },
        {
          "active": true,
          "defaultValue": false,
          "label": null,
          "validFor": null,
          "value": "Order_Subtotals__x"
        },
        {
          "active": true,
          "defaultValue": false,
          "label": null,
          "validFor": null,
          "value": "OrderItem"
        },
        {
          "active": true,
          "defaultValue": false,
          "label": null,
          "validFor": null,
          "value": "Orders__x"
        },
        {
          "active": true,
          "defaultValue": false,
          "label": null,
          "validFor": null,
          "value": "Orders_Qries__x"
        },
        {
          "active": true,
          "defaultValue": false,
          "label": null,
          "validFor": null,
          "value": "PartnerFundAllocation"
        },
        {
          "active": true,
          "defaultValue": false,
          "label": null,
          "validFor": null,
          "value": "PartnerFundClaim"
        },
        {
          "active": true,
          "defaultValue": false,
          "label": null,
          "validFor": null,
          "value": "PartnerFundRequest"
        },
        {
          "active": true,
          "defaultValue": false,
          "label": null,
          "validFor": null,
          "value": "PartnerMarketingBudget"
        },
        {
          "active": true,
          "defaultValue": false,
          "label": null,
          "validFor": null,
          "value": "PartyConsent"
        },
        {
          "active": true,
          "defaultValue": false,
          "label": null,
          "validFor": null,
          "value": "Product_Sales_for_1997__x"
        },
        {
          "active": true,
          "defaultValue": false,
          "label": null,
          "validFor": null,
          "value": "Product2"
        },
        {
          "active": true,
          "defaultValue": false,
          "label": null,
          "validFor": null,
          "value": "ProductConsumptionSchedule"
        },
        {
          "active": true,
          "defaultValue": false,
          "label": null,
          "validFor": null,
          "value": "Products__x"
        },
        {
          "active": true,
          "defaultValue": false,
          "label": null,
          "validFor": null,
          "value": "Products_Above_Average_Prices__x"
        },
        {
          "active": true,
          "defaultValue": false,
          "label": null,
          "validFor": null,
          "value": "Products_by_Categories__x"
        },
        {
          "active": true,
          "defaultValue": false,
          "label": null,
          "validFor": null,
          "value": "ProfileSkill"
        },
        {
          "active": true,
          "defaultValue": false,
          "label": null,
          "validFor": null,
          "value": "ProfileSkillEndorsement"
        },
        {
          "active": true,
          "defaultValue": false,
          "label": null,
          "validFor": null,
          "value": "ProfileSkillUser"
        },
        {
          "active": true,
          "defaultValue": false,
          "label": null,
          "validFor": null,
          "value": "QuickText"
        },
        {
          "active": true,
          "defaultValue": false,
          "label": null,
          "validFor": null,
          "value": "Recommendation"
        },
        {
          "active": true,
          "defaultValue": false,
          "label": null,
          "validFor": null,
          "value": "RecordAction"
        },
        {
          "active": true,
          "defaultValue": false,
          "label": null,
          "validFor": null,
          "value": "Reference__c"
        },
        {
          "active": true,
          "defaultValue": false,
          "label": null,
          "validFor": null,
          "value": "Regions__x"
        },
        {
          "active": true,
          "defaultValue": false,
          "label": null,
          "validFor": null,
          "value": "ReportAnomalyEventStore"
        },
        {
          "active": true,
          "defaultValue": false,
          "label": null,
          "validFor": null,
          "value": "Sales_by_Categories__x"
        },
        {
          "active": true,
          "defaultValue": false,
          "label": null,
          "validFor": null,
          "value": "Sales_Totals_by_Amounts__x"
        },
        {
          "active": true,
          "defaultValue": false,
          "label": null,
          "validFor": null,
          "value": "Scorecard"
        },
        {
          "active": true,
          "defaultValue": false,
          "label": null,
          "validFor": null,
          "value": "ScorecardAssociation"
        },
        {
          "active": true,
          "defaultValue": false,
          "label": null,
          "validFor": null,
          "value": "ScorecardMetric"
        },
        {
          "active": true,
          "defaultValue": false,
          "label": null,
          "validFor": null,
          "value": "Seller"
        },
        {
          "active": true,
          "defaultValue": false,
          "label": null,
          "validFor": null,
          "value": "SessionHijackingEventStore"
        },
        {
          "active": true,
          "defaultValue": false,
          "label": null,
          "validFor": null,
          "value": "Shippers__x"
        },
        {
          "active": true,
          "defaultValue": false,
          "label": null,
          "validFor": null,
          "value": "Social_Handle__c"
        },
        {
          "active": true,
          "defaultValue": false,
          "label": null,
          "validFor": null,
          "value": "SocialPersona"
        },
        {
          "active": true,
          "defaultValue": false,
          "label": null,
          "validFor": null,
          "value": "Solution"
        },
        {
          "active": true,
          "defaultValue": false,
          "label": null,
          "validFor": null,
          "value": "Summary_of_Sales_by_Quarters__x"
        },
        {
          "active": true,
          "defaultValue": false,
          "label": null,
          "validFor": null,
          "value": "Summary_of_Sales_by_Years__x"
        },
        {
          "active": true,
          "defaultValue": false,
          "label": null,
          "validFor": null,
          "value": "Suppliers__x"
        },
        {
          "active": true,
          "defaultValue": false,
          "label": null,
          "validFor": null,
          "value": "Task"
        },
        {
          "active": true,
          "defaultValue": false,
          "label": null,
          "validFor": null,
          "value": "Territories__x"
        },
        {
          "active": true,
          "defaultValue": false,
          "label": null,
          "validFor": null,
          "value": "testexternalobj__x"
        },
        {
          "active": true,
          "defaultValue": false,
          "label": null,
          "validFor": null,
          "value": "Tower__c"
        },
        {
          "active": true,
          "defaultValue": false,
          "label": null,
          "validFor": null,
          "value": "Trailhead_Superbadge__c"
        },
        {
          "active": true,
          "defaultValue": false,
          "label": null,
          "validFor": null,
          "value": "User"
        },
        {
          "active": true,
          "defaultValue": false,
          "label": null,
          "validFor": null,
          "value": "UserProvisioningRequest"
        },
        {
          "active": true,
          "defaultValue": false,
          "label": null,
          "validFor": null,
          "value": "Work_Experience__c"
        },
        {
          "active": true,
          "defaultValue": false,
          "label": null,
          "validFor": null,
          "value": "WorkBadge"
        },
        {
          "active": true,
          "defaultValue": false,
          "label": null,
          "validFor": null,
          "value": "WorkBadgeDefinition"
        },
        {
          "active": true,
          "defaultValue": false,
          "label": null,
          "validFor": null,
          "value": "WorkCoaching"
        },
        {
          "active": true,
          "defaultValue": false,
          "label": null,
          "validFor": null,
          "value": "WorkFeedback"
        },
        {
          "active": true,
          "defaultValue": false,
          "label": null,
          "validFor": null,
          "value": "WorkFeedbackQuestion"
        },
        {
          "active": true,
          "defaultValue": false,
          "label": null,
          "validFor": null,
          "value": "WorkFeedbackQuestionSet"
        },
        {
          "active": true,
          "defaultValue": false,
          "label": null,
          "validFor": null,
          "value": "WorkFeedbackRequest"
        },
        {
          "active": true,
          "defaultValue": false,
          "label": null,
          "validFor": null,
          "value": "WorkFeedbackTemplate"
        },
        {
          "active": true,
          "defaultValue": false,
          "label": null,
          "validFor": null,
          "value": "WorkPerformanceCycle"
        },
        {
          "active": true,
          "defaultValue": false,
          "label": null,
          "validFor": null,
          "value": "WorkReward"
        },
        {
          "active": true,
          "defaultValue": false,
          "label": null,
          "validFor": null,
          "value": "WorkRewardFund"
        },
        {
          "active": true,
          "defaultValue": false,
          "label": null,
          "validFor": null,
          "value": "WorkRewardFundType"
        },
        {
          "active": true,
          "defaultValue": false,
          "label": null,
          "validFor": null,
          "value": "WorkThanks"
        }
      ],
      "referenceTo": [],
      "relationshipName": null,
      "sortable": true,
      "type": "picklist"
    },
    {
      "aggregatable": true,
      "custom": false,
      "defaultValue": null,
      "extraTypeInfo": null,
      "filterable": true,
      "groupable": true,
      "inlineHelpText": null,
      "label": "Name",
      "name": "Name",
      "nillable": false,
      "picklistValues": [],
      "referenceTo": [],
      "relationshipName": null,
      "sortable": true,
      "type": "string"
    },
    {
      "aggregatable": false,
      "custom": false,
      "defaultValue": false,
      "extraTypeInfo": null,
      "filterable": true,
      "groupable": true,
      "inlineHelpText": null,
      "label": "Protected Component",
      "name": "IsProtected",
      "nillable": false,
      "picklistValues": [],
      "referenceTo": [],
      "relationshipName": null,
      "sortable": true,
      "type": "boolean"
    },
    {
      "aggregatable": false,
      "custom": false,
      "defaultValue": null,
      "extraTypeInfo": "plaintextarea",
      "filterable": false,
      "groupable": false,
      "inlineHelpText": null,
      "label": "URL",
      "name": "Url",
      "nillable": true,
      "picklistValues": [],
      "referenceTo": [],
      "relationshipName": null,
      "sortable": false,
      "type": "textarea"
    },
    {
      "aggregatable": true,
      "custom": false,
      "defaultValue": null,
      "extraTypeInfo": null,
      "filterable": true,
      "groupable": true,
      "inlineHelpText": null,
      "label": "Link Encoding",
      "name": "EncodingKey",
      "nillable": false,
      "picklistValues": [
        {
          "active": true,
          "defaultValue": false,
          "label": "Unicode (UTF-8)",
          "validFor": null,
          "value": "UTF-8"
        },
        {
          "active": true,
          "defaultValue": false,
          "label": "General US & Western Europe (ISO-8859-1, ISO-LATIN-1)",
          "validFor": null,
          "value": "ISO-8859-1"
        },
        {
          "active": true,
          "defaultValue": false,
          "label": "Japanese (Shift-JIS)",
          "validFor": null,
          "value": "Shift_JIS"
        },
        {
          "active": true,
          "defaultValue": false,
          "label": "Japanese (JIS)",
          "validFor": null,
          "value": "ISO-2022-JP"
        },
        {
          "active": true,
          "defaultValue": false,
          "label": "Japanese (EUC)",
          "validFor": null,
          "value": "EUC-JP"
        },
        {
          "active": true,
          "defaultValue": false,
          "label": "Korean (ks_c_5601-1987)",
          "validFor": null,
          "value": "ks_c_5601-1987"
        },
        {
          "active": true,
          "defaultValue": false,
          "label": "Traditional Chinese (Big5)",
          "validFor": null,
          "value": "Big5"
        },
        {
          "active": true,
          "defaultValue": false,
          "label": "Simplified Chinese (GB2312)",
          "validFor": null,
          "value": "GB2312"
        },
        {
          "active": true,
          "defaultValue": false,
          "label": "Traditional Chinese Hong Kong (Big5-HKSCS)",
          "validFor": null,
          "value": "Big5-HKSCS"
        },
        {
          "active": true,
          "defaultValue": false,
          "label": "Japanese (Shift-JIS_2004)",
          "validFor": null,
          "value": "x-SJIS_0213"
        }
      ],
      "referenceTo": [],
      "relationshipName": null,
      "sortable": true,
      "type": "picklist"
    },
    {
      "aggregatable": true,
      "custom": false,
      "defaultValue": null,
      "extraTypeInfo": null,
      "filterable": true,
      "groupable": true,
      "inlineHelpText": null,
      "label": "Content Source",
      "name": "LinkType",
      "nillable": false,
      "picklistValues": [
        {
          "active": true,
          "defaultValue": false,
          "label": "URL",
          "validFor": null,
          "value": "url"
        },
        {
          "active": true,
          "defaultValue": false,
          "label": "Custom S-Control",
          "validFor": null,
          "value": "sControl"
        },
        {
          "active": true,
          "defaultValue": false,
          "label": "OnClick JavaScript",
          "validFor": null,
          "value": "javascript"
        },
        {
          "active": true,
          "defaultValue": false,
          "label": "Visualforce Page",
          "validFor": null,
          "value": "page"
        },
        {
          "active": true,
          "defaultValue": false,
          "label": "Flow Definition",
          "validFor": null,
          "value": "flow"
        }
      ],
      "referenceTo": [],
      "relationshipName": null,
      "sortable": true,
      "type": "picklist"
    },
    {
      "aggregatable": true,
      "custom": false,
      "defaultValue": null,
      "extraTypeInfo": null,
      "filterable": true,
      "groupable": true,
      "inlineHelpText": null,
      "label": "Behavior",
      "name": "OpenType",
      "nillable": false,
      "picklistValues": [
        {
          "active": true,
          "defaultValue": false,
          "label": "Display in new window",
          "validFor": null,
          "value": "newWindow"
        },
        {
          "active": true,
          "defaultValue": false,
          "label": "Display in existing window with sidebar",
          "validFor": null,
          "value": "sidebar"
        },
        {
          "active": true,
          "defaultValue": false,
          "label": "Display in existing window without sidebar",
          "validFor": null,
          "value": "noSidebar"
        },
        {
          "active": true,
          "defaultValue": false,
          "label": "Display in existing window without sidebar or header",
          "validFor": null,
          "value": "replace"
        },
        {
          "active": true,
          "defaultValue": false,
          "label": "Execute JavaScript",
          "validFor": null,
          "value": "onClickJavaScript"
        }
      ],
      "referenceTo": [],
      "relationshipName": null,
      "sortable": true,
      "type": "picklist"
    },
    {
      "aggregatable": true,
      "custom": false,
      "defaultValue": null,
      "extraTypeInfo": null,
      "filterable": true,
      "groupable": true,
      "inlineHelpText": null,
      "label": "Height (in pixels)",
      "name": "Height",
      "nillable": true,
      "picklistValues": [],
      "referenceTo": [],
      "relationshipName": null,
      "sortable": true,
      "type": "int"
    },
    {
      "aggregatable": true,
      "custom": false,
      "defaultValue": null,
      "extraTypeInfo": null,
      "filterable": true,
      "groupable": true,
      "inlineHelpText": null,
      "label": "Width (in pixels)",
      "name": "Width",
      "nillable": true,
      "picklistValues": [],
      "referenceTo": [],
      "relationshipName": null,
      "sortable": true,
      "type": "int"
    },
    {
      "aggregatable": false,
      "custom": false,
      "defaultValue": false,
      "extraTypeInfo": null,
      "filterable": true,
      "groupable": true,
      "inlineHelpText": null,
      "label": "Show Address Bar",
      "name": "ShowsLocation",
      "nillable": false,
      "picklistValues": [],
      "referenceTo": [],
      "relationshipName": null,
      "sortable": true,
      "type": "boolean"
    },
    {
      "aggregatable": false,
      "custom": false,
      "defaultValue": false,
      "extraTypeInfo": null,
      "filterable": true,
      "groupable": true,
      "inlineHelpText": null,
      "label": "Show Scrollbars",
      "name": "HasScrollbars",
      "nillable": false,
      "picklistValues": [],
      "referenceTo": [],
      "relationshipName": null,
      "sortable": true,
      "type": "boolean"
    },
    {
      "aggregatable": false,
      "custom": false,
      "defaultValue": false,
      "extraTypeInfo": null,
      "filterable": true,
      "groupable": true,
      "inlineHelpText": null,
      "label": "Show Toolbars",
      "name": "HasToolbar",
      "nillable": false,
      "picklistValues": [],
      "referenceTo": [],
      "relationshipName": null,
      "sortable": true,
      "type": "boolean"
    },
    {
      "aggregatable": false,
      "custom": false,
      "defaultValue": false,
      "extraTypeInfo": null,
      "filterable": true,
      "groupable": true,
      "inlineHelpText": null,
      "label": "Show Menu Bar",
      "name": "HasMenubar",
      "nillable": false,
      "picklistValues": [],
      "referenceTo": [],
      "relationshipName": null,
      "sortable": true,
      "type": "boolean"
    },
    {
      "aggregatable": false,
      "custom": false,
      "defaultValue": false,
      "extraTypeInfo": null,
      "filterable": true,
      "groupable": true,
      "inlineHelpText": null,
      "label": "Show Status Bar",
      "name": "ShowsStatus",
      "nillable": false,
      "picklistValues": [],
      "referenceTo": [],
      "relationshipName": null,
      "sortable": true,
      "type": "boolean"
    },
    {
      "aggregatable": false,
      "custom": false,
      "defaultValue": false,
      "extraTypeInfo": null,
      "filterable": true,
      "groupable": true,
      "inlineHelpText": null,
      "label": "Resizeable",
      "name": "IsResizable",
      "nillable": false,
      "picklistValues": [],
      "referenceTo": [],
      "relationshipName": null,
      "sortable": true,
      "type": "boolean"
    },
    {
      "aggregatable": true,
      "custom": false,
      "defaultValue": null,
      "extraTypeInfo": null,
      "filterable": true,
      "groupable": true,
      "inlineHelpText": null,
      "label": "Window Position",
      "name": "Position",
      "nillable": true,
      "picklistValues": [
        {
          "active": true,
          "defaultValue": false,
          "label": null,
          "validFor": null,
          "value": "fullScreen"
        },
        {
          "active": true,
          "defaultValue": false,
          "label": null,
          "validFor": null,
          "value": "none"
        },
        {
          "active": true,
          "defaultValue": false,
          "label": null,
          "validFor": null,
          "value": "topLeft"
        }
      ],
      "referenceTo": [],
      "relationshipName": null,
      "sortable": true,
      "type": "picklist"
    },
    {
      "aggregatable": true,
      "custom": false,
      "defaultValue": null,
      "extraTypeInfo": null,
      "filterable": true,
      "groupable": true,
      "inlineHelpText": null,
      "label": "Custom S-Control ID",
      "name": "ScontrolId",
      "nillable": true,
      "picklistValues": [],
      "referenceTo": [
        "ApexPage",
        "Scontrol"
      ],
      "relationshipName": null,
      "sortable": true,
      "type": "reference"
    },
    {
      "aggregatable": true,
      "custom": false,
      "defaultValue": null,
      "extraTypeInfo": null,
      "filterable": true,
      "groupable": true,
      "inlineHelpText": null,
      "label": "Label",
      "name": "MasterLabel",
      "nillable": true,
      "picklistValues": [],
      "referenceTo": [],
      "relationshipName": null,
      "sortable": true,
      "type": "string"
    },
    {
      "aggregatable": true,
      "custom": false,
      "defaultValue": null,
      "extraTypeInfo": "plaintextarea",
      "filterable": true,
      "groupable": false,
      "inlineHelpText": null,
      "label": "Description",
      "name": "Description",
      "nillable": true,
      "picklistValues": [],
      "referenceTo": [],
      "relationshipName": null,
      "sortable": true,
      "type": "textarea"
    },
    {
      "aggregatable": true,
      "custom": false,
      "defaultValue": "L",
      "extraTypeInfo": null,
      "filterable": true,
      "groupable": true,
      "inlineHelpText": null,
      "label": "Display Type",
      "name": "DisplayType",
      "nillable": false,
      "picklistValues": [
        {
          "active": true,
          "defaultValue": true,
          "label": "Detail Page Link",
          "validFor": null,
          "value": "L"
        },
        {
          "active": true,
          "defaultValue": false,
          "label": "Detail Page Button",
          "validFor": null,
          "value": "B"
        },
        {
          "active": true,
          "defaultValue": false,
          "label": "List Button",
          "validFor": null,
          "value": "M"
        }
      ],
      "referenceTo": [],
      "relationshipName": null,
      "sortable": true,
      "type": "picklist"
    },
    {
      "aggregatable": false,
      "custom": false,
      "defaultValue": false,
      "extraTypeInfo": null,
      "filterable": true,
      "groupable": true,
      "inlineHelpText": null,
      "label": "Require Row Selection",
      "name": "RequireRowSelection",
      "nillable": false,
      "picklistValues": [],
      "referenceTo": [],
      "relationshipName": null,
      "sortable": true,
      "type": "boolean"
    },
    {
      "aggregatable": true,
      "custom": false,
      "defaultValue": null,
      "extraTypeInfo": null,
      "filterable": true,
      "groupable": true,
      "inlineHelpText": null,
      "label": "Namespace Prefix",
      "name": "NamespacePrefix",
      "nillable": true,
      "picklistValues": [],
      "referenceTo": [],
      "relationshipName": null,
      "sortable": true,
      "type": "string"
    },
    {
      "aggregatable": true,
      "custom": false,
      "defaultValue": null,
      "extraTypeInfo": null,
      "filterable": true,
      "groupable": false,
      "inlineHelpText": null,
      "label": "Created Date",
      "name": "CreatedDate",
      "nillable": false,
      "picklistValues": [],
      "referenceTo": [],
      "relationshipName": null,
      "sortable": true,
      "type": "datetime"
    },
    {
      "aggregatable": true,
      "custom": false,
      "defaultValue": null,
      "extraTypeInfo": null,
      "filterable": true,
      "groupable": true,
      "inlineHelpText": null,
      "label": "Created By ID",
      "name": "CreatedById",
      "nillable": false,
      "picklistValues": [],
      "referenceTo": [
        "User"
      ],
      "relationshipName": "CreatedBy",
      "sortable": true,
      "type": "reference"
    },
    {
      "aggregatable": true,
      "custom": false,
      "defaultValue": null,
      "extraTypeInfo": null,
      "filterable": true,
      "groupable": false,
      "inlineHelpText": null,
      "label": "Last Modified Date",
      "name": "LastModifiedDate",
      "nillable": false,
      "picklistValues": [],
      "referenceTo": [],
      "relationshipName": null,
      "sortable": true,
      "type": "datetime"
    },
    {
      "aggregatable": true,
      "custom": false,
      "defaultValue": null,
      "extraTypeInfo": null,
      "filterable": true,
      "groupable": true,
      "inlineHelpText": null,
      "label": "Last Modified By ID",
      "name": "LastModifiedById",
      "nillable": false,
      "picklistValues": [],
      "referenceTo": [
        "User"
      ],
      "relationshipName": "LastModifiedBy",
      "sortable": true,
      "type": "reference"
    },
    {
      "aggregatable": true,
      "custom": false,
      "defaultValue": null,
      "extraTypeInfo": null,
      "filterable": true,
      "groupable": false,
      "inlineHelpText": null,
      "label": "System Modstamp",
      "name": "SystemModstamp",
      "nillable": false,
      "picklistValues": [],
      "referenceTo": [],
      "relationshipName": null,
      "sortable": true,
      "type": "datetime"
    }
  ],
  "label": "Custom Button or Link",
  "childRelationships": [],
  "custom": false,
  "name": "WebLink",
  "queryable": true
}